{
  "disclaimer": "Heuristische Elliott-Wellen-Auszählung, unvalidiert. Keine Anlageberatung.",
  "generated_in_seconds": 83.4,
  "generator": "elliott_pipeline",
  "markets": {
    "DE": {
      "candidates": [
        {
          "appearance_count": 1,
          "change_abs": 0.1,
          "change_pct": 0.464,
          "chart_points": [
            {
              "date": "2026-03-10",
              "index": 412,
              "kind": "H",
              "price": 18.9719
            },
            {
              "date": "2026-03-26",
              "index": 424,
              "kind": "L",
              "price": 16.6991
            },
            {
              "date": "2026-04-17",
              "index": 438,
              "kind": "H",
              "price": 19.7905
            },
            {
              "date": "2026-05-04",
              "index": 448,
              "kind": "L",
              "price": 18.1052
            },
            {
              "date": "2026-05-07",
              "index": 451,
              "kind": "H",
              "price": 19.1645
            },
            {
              "date": "2026-05-21",
              "index": 461,
              "kind": "L",
              "price": 17.94
            },
            {
              "date": "2026-06-02",
              "index": 469,
              "kind": "H",
              "price": 19.08
            },
            {
              "date": "2026-06-11",
              "index": 476,
              "kind": "L",
              "price": 18.1
            },
            {
              "date": "2026-06-19",
              "index": 482,
              "kind": "H",
              "price": 19.64
            },
            {
              "date": "2026-06-29",
              "index": 488,
              "kind": "L",
              "price": 18.36
            },
            {
              "date": "2026-07-06",
              "index": 493,
              "kind": "H",
              "price": 19.8
            },
            {
              "date": "2026-07-08",
              "index": 495,
              "kind": "L",
              "price": 18.92
            }
          ],
          "close": 21.65,
          "company_name": "Wacker Neuson SE",
          "count_label": "Impuls 1–5 · Long-Setup am Ende W2 (W3 erwartet)",
          "count_wave_labels": [
            {
              "index": 9,
              "wave": 0
            },
            {
              "index": 10,
              "wave": 1
            },
            {
              "index": 11,
              "wave": 2
            }
          ],
          "direction": "long",
          "higher_degree": {
            "count_label": "Impuls 1–5 · Long-Setup am Ende W2 (W3 erwartet)",
            "invalidation_price": 16.7184,
            "target_zone": {
              "high": 23.0707,
              "low": 21.1721
            },
            "target_zone_extended": {
              "high": 26.1428,
              "low": 23.0707
            }
          },
          "invalidation_price": 18.36,
          "name": "WAC.DE",
          "score_heuristic": 79.08,
          "sector": "Industrials",
          "status": "heuristisch · unvalidiert",
          "target_zone": {
            "high": 21.2499,
            "low": 20.36
          },
          "target_zone_extended": {
            "high": 22.6899,
            "low": 21.2499
          },
          "ticker": "WAC.DE"
        },
        {
          "appearance_count": 1,
          "change_abs": -0.165,
          "change_pct": -1.353,
          "chart_points": [
            {
              "date": "2026-02-11",
              "index": 393,
              "kind": "H",
              "price": 12.275
            },
            {
              "date": "2026-02-13",
              "index": 395,
              "kind": "L",
              "price": 10.555
            },
            {
              "date": "2026-02-20",
              "index": 400,
              "kind": "H",
              "price": 11.32
            },
            {
              "date": "2026-03-30",
              "index": 426,
              "kind": "L",
              "price": 7.188
            },
            {
              "date": "2026-04-17",
              "index": 438,
              "kind": "H",
              "price": 9.264
            },
            {
              "date": "2026-04-28",
              "index": 445,
              "kind": "L",
              "price": 8.746
            },
            {
              "date": "2026-05-06",
              "index": 450,
              "kind": "H",
              "price": 11.06
            },
            {
              "date": "2026-05-12",
              "index": 454,
              "kind": "L",
              "price": 9.9
            },
            {
              "date": "2026-06-03",
              "index": 470,
              "kind": "H",
              "price": 11.83
            },
            {
              "date": "2026-06-29",
              "index": 488,
              "kind": "L",
              "price": 10.075
            },
            {
              "date": "2026-07-06",
              "index": 493,
              "kind": "H",
              "price": 12.37
            },
            {
              "date": "2026-07-09",
              "index": 496,
              "kind": "L",
              "price": 11.275
            }
          ],
          "close": 12.03,
          "company_name": "thyssenkrupp AG",
          "count_label": "Impuls 1–5 · Long-Setup am Ende W2 (W3 erwartet)",
          "count_wave_labels": [
            {
              "index": 9,
              "wave": 0
            },
            {
              "index": 10,
              "wave": 1
            },
            {
              "index": 11,
              "wave": 2
            }
          ],
          "direction": "long",
          "higher_degree": null,
          "invalidation_price": 10.075,
          "name": "TKA.DE",
          "score_heuristic": 76.95,
          "sector": "Materials",
          "status": "heuristisch · unvalidiert",
          "target_zone": {
            "high": 14.9883,
            "low": 13.57
          },
          "target_zone_extended": {
            "high": 17.2833,
            "low": 14.9883
          },
          "ticker": "TKA.DE"
        },
        {
          "appearance_count": 1,
          "change_abs": 0.65,
          "change_pct": 1.0383,
          "chart_points": [
            {
              "date": "2025-11-27",
              "index": 344,
              "kind": "H",
              "price": 57.3132
            },
            {
              "date": "2025-12-08",
              "index": 351,
              "kind": "L",
              "price": 53.6455
            },
            {
              "date": "2026-01-26",
              "index": 381,
              "kind": "H",
              "price": 61.2253
            },
            {
              "date": "2026-01-28",
              "index": 383,
              "kind": "L",
              "price": 58.2423
            },
            {
              "date": "2026-02-27",
              "index": 405,
              "kind": "H",
              "price": 64.4529
            },
            {
              "date": "2026-03-06",
              "index": 410,
              "kind": "L",
              "price": 59.5138
            },
            {
              "date": "2026-03-18",
              "index": 418,
              "kind": "H",
              "price": 62.3501
            },
            {
              "date": "2026-03-27",
              "index": 425,
              "kind": "L",
              "price": 58.2423
            },
            {
              "date": "2026-04-17",
              "index": 438,
              "kind": "H",
              "price": 61.5676
            },
            {
              "date": "2026-06-03",
              "index": 470,
              "kind": "L",
              "price": 53.7
            },
            {
              "date": "2026-07-03",
              "index": 492,
              "kind": "H",
              "price": 63.3
            },
            {
              "date": "2026-07-14",
              "index": 499,
              "kind": "L",
              "price": 58.75
            }
          ],
          "close": 63.25,
          "company_name": "GEA Group AG",
          "count_label": "Impuls 1–5 · Long-Setup am Ende W2 (W3 erwartet)",
          "count_wave_labels": [
            {
              "index": 9,
              "wave": 0
            },
            {
              "index": 10,
              "wave": 1
            },
            {
              "index": 11,
              "wave": 2
            }
          ],
          "direction": "long",
          "higher_degree": null,
          "invalidation_price": 53.7,
          "name": "G1A.DE",
          "score_heuristic": 76.53,
          "sector": "Industrials",
          "status": "heuristisch · unvalidiert",
          "target_zone": {
            "high": 74.2828,
            "low": 68.35
          },
          "target_zone_extended": {
            "high": 83.8828,
            "low": 74.2828
          },
          "ticker": "G1A.DE"
        },
        {
          "appearance_count": 1,
          "change_abs": 3.02,
          "change_pct": 3.9079,
          "chart_points": [
            {
              "date": "2026-03-18",
              "index": 418,
              "kind": "H",
              "price": 83.4811
            },
            {
              "date": "2026-03-27",
              "index": 425,
              "kind": "L",
              "price": 66.6855
            },
            {
              "date": "2026-04-02",
              "index": 429,
              "kind": "H",
              "price": 82.8351
            },
            {
              "date": "2026-04-10",
              "index": 433,
              "kind": "L",
              "price": 76.2461
            },
            {
              "date": "2026-04-20",
              "index": 439,
              "kind": "H",
              "price": 81.8513
            },
            {
              "date": "2026-04-24",
              "index": 443,
              "kind": "L",
              "price": 72.569
            },
            {
              "date": "2026-05-05",
              "index": 449,
              "kind": "H",
              "price": 80.281
            },
            {
              "date": "2026-05-11",
              "index": 453,
              "kind": "L",
              "price": 70.7801
            },
            {
              "date": "2026-05-28",
              "index": 466,
              "kind": "H",
              "price": 90.0
            },
            {
              "date": "2026-06-25",
              "index": 486,
              "kind": "L",
              "price": 64.34
            },
            {
              "date": "2026-07-07",
              "index": 494,
              "kind": "H",
              "price": 80.92
            },
            {
              "date": "2026-07-14",
              "index": 499,
              "kind": "L",
              "price": 73.16
            }
          ],
          "close": 80.3,
          "company_name": "Hensoldt AG",
          "count_label": "Impuls 1–5 · Long-Setup am Ende W2 (W3 erwartet)",
          "count_wave_labels": [
            {
              "index": 9,
              "wave": 0
            },
            {
              "index": 10,
              "wave": 1
            },
            {
              "index": 11,
              "wave": 2
            }
          ],
          "direction": "long",
          "higher_degree": null,
          "invalidation_price": 64.34,
          "name": "HAG.DE",
          "score_heuristic": 75.74,
          "sector": "Industrials",
          "status": "heuristisch · unvalidiert",
          "target_zone": {
            "high": 99.9864,
            "low": 89.74
          },
          "target_zone_extended": {
            "high": 116.5664,
            "low": 99.9864
          },
          "ticker": "HAG.DE"
        },
        {
          "appearance_count": 1,
          "change_abs": 0.5,
          "change_pct": 0.8477,
          "chart_points": [
            {
              "date": "2026-03-02",
              "index": 406,
              "kind": "H",
              "price": 53.8371
            },
            {
              "date": "2026-03-05",
              "index": 409,
              "kind": "L",
              "price": 51.5816
            },
            {
              "date": "2026-03-17",
              "index": 417,
              "kind": "H",
              "price": 57.5047
            },
            {
              "date": "2026-03-27",
              "index": 425,
              "kind": "L",
              "price": 53.6017
            },
            {
              "date": "2026-04-30",
              "index": 447,
              "kind": "H",
              "price": 60.78
            },
            {
              "date": "2026-05-15",
              "index": 457,
              "kind": "L",
              "price": 55.2
            },
            {
              "date": "2026-05-25",
              "index": 463,
              "kind": "H",
              "price": 57.34
            },
            {
              "date": "2026-05-28",
              "index": 466,
              "kind": "L",
              "price": 54.48
            },
            {
              "date": "2026-06-11",
              "index": 476,
              "kind": "H",
              "price": 57.5
            },
            {
              "date": "2026-06-26",
              "index": 487,
              "kind": "L",
              "price": 54.06
            },
            {
              "date": "2026-07-03",
              "index": 492,
              "kind": "H",
              "price": 57.82
            },
            {
              "date": "2026-07-16",
              "index": 501,
              "kind": "L",
              "price": 55.6
            }
          ],
          "close": 59.48,
          "company_name": "RWE AG",
          "count_label": "Impuls 1–5 · Long-Setup am Ende W2 (W3 erwartet)",
          "count_wave_labels": [
            {
              "index": 9,
              "wave": 0
            },
            {
              "index": 10,
              "wave": 1
            },
            {
              "index": 11,
              "wave": 2
            }
          ],
          "direction": "long",
          "higher_degree": null,
          "invalidation_price": 54.06,
          "name": "RWE.DE",
          "score_heuristic": 74.99,
          "sector": "Utilities",
          "status": "heuristisch · unvalidiert",
          "target_zone": {
            "high": 61.6837,
            "low": 59.36
          },
          "target_zone_extended": {
            "high": 65.4437,
            "low": 61.6837
          },
          "ticker": "RWE.DE"
        }
      ],
      "candidates_found": 26,
      "diag": {
        "dead_tickers": [
          {
            "reason": "empty_data",
            "ticker": "1COV.DE"
          },
          {
            "reason": "empty_data",
            "ticker": "CTS.DE"
          },
          {
            "reason": "empty_data",
            "ticker": "UN01.DE"
          },
          {
            "reason": "empty_data",
            "ticker": "SHA.DE"
          },
          {
            "reason": "empty_data",
            "ticker": "COP.DE"
          }
        ],
        "higher_degree_count": 1,
        "reason_counts": {
          "empty_data": 5,
          "fetch_error": 0,
          "no_valid_count": 63,
          "short_setup_excluded": 28,
          "too_few_pivots": 0
        },
        "top_count": 5
      },
      "evaluated": 122,
      "label": "Deutschland",
      "skipped": 96,
      "universe_size": 122
    },
    "US": {
      "candidates": [
        {
          "appearance_count": 1,
          "change_abs": -6.87,
          "change_pct": -2.0079,
          "chart_points": [
            {
              "date": "2026-01-07",
              "index": 366,
              "kind": "H",
              "price": 193.9
            },
            {
              "date": "2026-02-05",
              "index": 386,
              "kind": "L",
              "price": 154.77
            },
            {
              "date": "2026-02-13",
              "index": 392,
              "kind": "H",
              "price": 166.95
            },
            {
              "date": "2026-02-24",
              "index": 398,
              "kind": "L",
              "price": 141.67
            },
            {
              "date": "2026-03-19",
              "index": 415,
              "kind": "H",
              "price": 169.74
            },
            {
              "date": "2026-03-27",
              "index": 421,
              "kind": "L",
              "price": 147.02
            },
            {
              "date": "2026-04-08",
              "index": 428,
              "kind": "H",
              "price": 173.78
            },
            {
              "date": "2026-04-10",
              "index": 430,
              "kind": "L",
              "price": 155.73
            },
            {
              "date": "2026-06-01",
              "index": 465,
              "kind": "H",
              "price": 300.48
            },
            {
              "date": "2026-06-09",
              "index": 471,
              "kind": "L",
              "price": 260.52
            },
            {
              "date": "2026-07-06",
              "index": 488,
              "kind": "H",
              "price": 357.53
            },
            {
              "date": "2026-07-08",
              "index": 490,
              "kind": "L",
              "price": 320.59
            }
          ],
          "close": 335.28,
          "company_name": "Palo Alto Networks Inc.",
          "count_label": "Impuls 1–5 · Long-Setup am Ende W4 (W5 erwartet)",
          "count_wave_labels": [
            {
              "index": 7,
              "wave": 0
            },
            {
              "index": 8,
              "wave": 1
            },
            {
              "index": 9,
              "wave": 2
            },
            {
              "index": 10,
              "wave": 3
            },
            {
              "index": 11,
              "wave": 4
            }
          ],
          "direction": "long",
          "higher_degree": null,
          "invalidation_price": 300.48,
          "name": "PANW",
          "score_heuristic": 89.84,
          "sector": "Technology",
          "status": "heuristisch · unvalidiert",
          "target_zone": {
            "high": 465.34,
            "low": 410.0455
          },
          "target_zone_extended": {
            "high": 445.3024,
            "low": 397.6776
          },
          "ticker": "PANW"
        },
        {
          "appearance_count": 1,
          "change_abs": -10.63,
          "change_pct": -1.8829,
          "chart_points": [
            {
              "date": "2026-02-25",
              "index": 399,
              "kind": "H",
              "price": 394.4596
            },
            {
              "date": "2026-03-06",
              "index": 406,
              "kind": "L",
              "price": 324.3368
            },
            {
              "date": "2026-03-24",
              "index": 418,
              "kind": "H",
              "price": 373.5256
            },
            {
              "date": "2026-03-30",
              "index": 422,
              "kind": "L",
              "price": 322.7188
            },
            {
              "date": "2026-04-10",
              "index": 430,
              "kind": "H",
              "price": 398.994
            },
            {
              "date": "2026-04-16",
              "index": 434,
              "kind": "L",
              "price": 389.4159
            },
            {
              "date": "2026-04-24",
              "index": 440,
              "kind": "H",
              "price": 416.5222
            },
            {
              "date": "2026-04-28",
              "index": 442,
              "kind": "L",
              "price": 380.6368
            },
            {
              "date": "2026-05-11",
              "index": 451,
              "kind": "H",
              "price": 443.0692
            },
            {
              "date": "2026-05-19",
              "index": 457,
              "kind": "L",
              "price": 406.4048
            },
            {
              "date": "2026-06-30",
              "index": 485,
              "kind": "H",
              "price": 723.0
            },
            {
              "date": "2026-07-07",
              "index": 489,
              "kind": "L",
              "price": 554.5
            }
          ],
          "close": 553.92,
          "company_name": "Applied Materials Inc.",
          "count_label": "Impuls 1–5 · Long-Setup am Ende W4 (W5 erwartet)",
          "count_wave_labels": [
            {
              "index": 7,
              "wave": 0
            },
            {
              "index": 8,
              "wave": 1
            },
            {
              "index": 9,
              "wave": 2
            },
            {
              "index": 10,
              "wave": 3
            },
            {
              "index": 11,
              "wave": 4
            }
          ],
          "direction": "long",
          "higher_degree": null,
          "invalidation_price": 443.0692,
          "name": "AMAT",
          "score_heuristic": 85.7,
          "sector": "Technology",
          "status": "heuristisch · unvalidiert",
          "target_zone": {
            "high": 616.9324,
            "low": 593.0832
          },
          "target_zone_extended": {
            "high": 766.0805,
            "low": 685.2828
          },
          "ticker": "AMAT"
        },
        {
          "appearance_count": 1,
          "change_abs": -0.1,
          "change_pct": -0.1071,
          "chart_points": [
            {
              "date": "2026-02-02",
              "index": 383,
              "kind": "H",
              "price": 78.6592
            },
            {
              "date": "2026-02-05",
              "index": 386,
              "kind": "L",
              "price": 74.7472
            },
            {
              "date": "2026-02-18",
              "index": 394,
              "kind": "H",
              "price": 78.6176
            },
            {
              "date": "2026-03-27",
              "index": 421,
              "kind": "L",
              "price": 67.1852
            },
            {
              "date": "2026-04-17",
              "index": 435,
              "kind": "H",
              "price": 77.4862
            },
            {
              "date": "2026-04-23",
              "index": 439,
              "kind": "L",
              "price": 75.4816
            },
            {
              "date": "2026-05-01",
              "index": 445,
              "kind": "H",
              "price": 79.6199
            },
            {
              "date": "2026-05-11",
              "index": 451,
              "kind": "L",
              "price": 77.387
            },
            {
              "date": "2026-05-21",
              "index": 459,
              "kind": "H",
              "price": 84.3
            },
            {
              "date": "2026-06-03",
              "index": 467,
              "kind": "L",
              "price": 80.96
            },
            {
              "date": "2026-06-12",
              "index": 474,
              "kind": "H",
              "price": 88.84
            },
            {
              "date": "2026-06-24",
              "index": 481,
              "kind": "L",
              "price": 84.6
            }
          ],
          "close": 93.27,
          "company_name": "MetLife Inc.",
          "count_label": "Impuls 1–5 · Long-Setup am Ende W4 (W5 erwartet)",
          "count_wave_labels": [
            {
              "index": 7,
              "wave": 0
            },
            {
              "index": 8,
              "wave": 1
            },
            {
              "index": 9,
              "wave": 2
            },
            {
              "index": 10,
              "wave": 3
            },
            {
              "index": 11,
              "wave": 4
            }
          ],
          "direction": "long",
          "higher_degree": null,
          "invalidation_price": 84.3,
          "name": "MET",
          "score_heuristic": 84.35,
          "sector": "Financials",
          "status": "heuristisch · unvalidiert",
          "target_zone": {
            "high": 91.513,
            "low": 88.8722
          },
          "target_zone_extended": {
            "high": 91.6779,
            "low": 88.975
          },
          "ticker": "MET"
        },
        {
          "appearance_count": 1,
          "change_abs": 1.24,
          "change_pct": 1.7752,
          "chart_points": [
            {
              "date": "2025-12-17",
              "index": 353,
              "kind": "H",
              "price": 58.8865
            },
            {
              "date": "2026-01-07",
              "index": 366,
              "kind": "L",
              "price": 55.9182
            },
            {
              "date": "2026-01-16",
              "index": 373,
              "kind": "H",
              "price": 59.8858
            },
            {
              "date": "2026-01-23",
              "index": 377,
              "kind": "L",
              "price": 58.3869
            },
            {
              "date": "2026-02-13",
              "index": 392,
              "kind": "H",
              "price": 65.1563
            },
            {
              "date": "2026-03-20",
              "index": 416,
              "kind": "L",
              "price": 58.7913
            },
            {
              "date": "2026-04-10",
              "index": 430,
              "kind": "H",
              "price": 63.5932
            },
            {
              "date": "2026-04-22",
              "index": 438,
              "kind": "L",
              "price": 60.3457
            },
            {
              "date": "2026-04-30",
              "index": 444,
              "kind": "H",
              "price": 63.8606
            },
            {
              "date": "2026-05-07",
              "index": 449,
              "kind": "L",
              "price": 60.9992
            },
            {
              "date": "2026-05-21",
              "index": 459,
              "kind": "H",
              "price": 67.613
            },
            {
              "date": "2026-06-01",
              "index": 465,
              "kind": "L",
              "price": 64.61
            }
          ],
          "close": 71.09,
          "company_name": "Dominion Energy Inc.",
          "count_label": "Impuls 1–5 · Long-Setup am Ende W4 (W5 erwartet)",
          "count_wave_labels": [
            {
              "index": 7,
              "wave": 0
            },
            {
              "index": 8,
              "wave": 1
            },
            {
              "index": 9,
              "wave": 2
            },
            {
              "index": 10,
              "wave": 3
            },
            {
              "index": 11,
              "wave": 4
            }
          ],
          "direction": "long",
          "higher_degree": {
            "count_label": "Impuls 1–5 · Long-Setup am Ende W2 (W3 erwartet)",
            "invalidation_price": 58.7913,
            "target_zone": {
              "high": 68.8875,
              "low": 65.9199
            },
            "target_zone_extended": {
              "high": 73.6894,
              "low": 68.8875
            }
          },
          "invalidation_price": 63.8606,
          "name": "D",
          "score_heuristic": 83.87,
          "sector": "Utilities",
          "status": "heuristisch · unvalidiert",
          "target_zone": {
            "high": 68.1248,
            "low": 66.7822
          },
          "target_zone_extended": {
            "high": 69.1011,
            "low": 67.3861
          },
          "ticker": "D"
        },
        {
          "appearance_count": 1,
          "change_abs": 0.26,
          "change_pct": 0.2192,
          "chart_points": [
            {
              "date": "2026-01-08",
              "index": 367,
              "kind": "H",
              "price": 115.5562
            },
            {
              "date": "2026-02-05",
              "index": 386,
              "kind": "L",
              "price": 97.1599
            },
            {
              "date": "2026-02-18",
              "index": 394,
              "kind": "H",
              "price": 102.9272
            },
            {
              "date": "2026-03-13",
              "index": 411,
              "kind": "L",
              "price": 90.763
            },
            {
              "date": "2026-04-01",
              "index": 424,
              "kind": "H",
              "price": 96.6626
            },
            {
              "date": "2026-04-08",
              "index": 428,
              "kind": "L",
              "price": 95.3504
            },
            {
              "date": "2026-04-20",
              "index": 436,
              "kind": "H",
              "price": 101.2204
            },
            {
              "date": "2026-04-24",
              "index": 440,
              "kind": "L",
              "price": 92.9432
            },
            {
              "date": "2026-05-21",
              "index": 459,
              "kind": "H",
              "price": 102.8384
            },
            {
              "date": "2026-06-01",
              "index": 465,
              "kind": "L",
              "price": 100.49
            },
            {
              "date": "2026-06-16",
              "index": 476,
              "kind": "H",
              "price": 109.16
            },
            {
              "date": "2026-06-24",
              "index": 481,
              "kind": "L",
              "price": 106.26
            }
          ],
          "close": 118.85,
          "company_name": "Prudential Financial Inc.",
          "count_label": "Impuls 1–5 · Long-Setup am Ende W4 (W5 erwartet)",
          "count_wave_labels": [
            {
              "index": 7,
              "wave": 0
            },
            {
              "index": 8,
              "wave": 1
            },
            {
              "index": 9,
              "wave": 2
            },
            {
              "index": 10,
              "wave": 3
            },
            {
              "index": 11,
              "wave": 4
            }
          ],
          "direction": "long",
          "higher_degree": null,
          "invalidation_price": 102.8384,
          "name": "PRU",
          "score_heuristic": 83.66,
          "sector": "Financials",
          "status": "heuristisch · unvalidiert",
          "target_zone": {
            "high": 116.1551,
            "low": 112.3752
          },
          "target_zone_extended": {
            "high": 116.282,
            "low": 112.4548
          },
          "ticker": "PRU"
        }
      ],
      "candidates_found": 87,
      "diag": {
        "dead_tickers": [
          {
            "reason": "empty_data",
            "ticker": "MMC"
          },
          {
            "reason": "empty_data",
            "ticker": "FI"
          },
          {
            "reason": "empty_data",
            "ticker": "HES"
          }
        ],
        "higher_degree_count": 1,
        "reason_counts": {
          "empty_data": 3,
          "fetch_error": 0,
          "no_valid_count": 110,
          "short_setup_excluded": 39,
          "too_few_pivots": 0
        },
        "top_count": 5
      },
      "evaluated": 239,
      "label": "USA",
      "skipped": 152,
      "universe_size": 239
    }
  },
  "run_timestamp_utc": "2026-07-23T11:18:05Z",
  "schema_version": 1,
  "watchlist": {
    "diag": {
      "error": 0,
      "no_setup": 0,
      "setup": 0
    },
    "entries": []
  }
}
